vbtex/.DS_Store
vbtex/__init__.py
vbtex/__main__.py
vbtex/choice_option.py
vbtex/framed.py
vbtex/main.py
vbtex/padded.py
vbtex-0.1.19.dist-info/METADATA
vbtex-0.1.19.dist-info/WHEEL
vbtex-0.1.19.dist-info/entry_points.txt
vbtex-0.1.19.dist-info/RECORD
