Metadata-Version: 2.1
Name: vbtex
Version: 0.1.19
Summary: Added archiving for tex file(content.tex)
Author: vaibhavblayer
Author-email: vaibhavblayer@gmail.com
Requires-Python: >=3.11,<4.0
Classifier: Programming Language :: Python :: 3
Classifier: Programming Language :: Python :: 3.11
